replit_code_exec/__init__.py
replit_code_exec-0.0.1.dist-info/LICENSE
replit_code_exec-0.0.1.dist-info/METADATA
replit_code_exec-0.0.1.dist-info/WHEEL
replit_code_exec-0.0.1.dist-info/RECORD
