Metadata-Version: 2.1
Name: replit-code-exec
Version: 0.0.1
Summary: A library for interacting with Replit's code-exec API
Home-page: https://github.com/replit/replit-code-exec
License: ISC
Author: Repl.it
Author-email: contact@repl.it
Requires-Python: >=3.9,<4.0
Classifier: License :: OSI Approved
Classifier: License :: OSI Approved :: ISC License (ISCL)
Classifier: Operating System :: OS Independent
Classifier: Programming Language :: Python :: 3
Classifier: Programming Language :: Python :: 3.9
Classifier: Programming Language :: Python :: 3.10
Classifier: Programming Language :: Python :: 3.11
Requires-Dist: instructor (>=0.2.7,<0.3.0)
Requires-Dist: requests (>=2.31.0,<3.0.0)
Project-URL: Repository, https://github.com/replit/replit-code-exec
